pySEI/__init__.py
pySEI/config.ini
pysei-1.4.3.dist-info/licenses/LICENSE
pysei-1.4.3.dist-info/METADATA
pysei-1.4.3.dist-info/WHEEL
pysei-1.4.3.dist-info/top_level.txt
pysei-1.4.3.dist-info/RECORD
