Metadata-Version: 2.4
Name: pySEI
Version: 1.4.3
Summary: Pacote para interagir com o SEI
Home-page: https://github.com/danielsioli/pySEI
Author: Daniel Oliveira
Author-email: danielsioli@gmail.com
License: Creative Commons Attribution-Noncommercial-Share Alike license
Keywords: anatel,sei
Classifier: Development Status :: 4 - Beta
Classifier: Intended Audience :: Developers
Classifier: Topic :: Internet :: WWW/HTTP
Classifier: Programming Language :: Python :: 3
Classifier: Programming Language :: Python :: 3.3
Classifier: Programming Language :: Python :: 3.4
Classifier: Programming Language :: Python :: 3.5
Requires-Python: >=3.6
License-File: LICENSE
Requires-Dist: selenium
Requires-Dist: webdriver_manager
Requires-Dist: ConfigParser
Requires-Dist: pandas
Dynamic: author
Dynamic: author-email
Dynamic: classifier
Dynamic: description
Dynamic: description-content-type
Dynamic: home-page
Dynamic: keywords
Dynamic: license
Dynamic: license-file
Dynamic: requires-dist
Dynamic: requires-python
Dynamic: summary
